cg/rootutils/__init__.py
cg/rootutils/py.typed
cg_rootutils-0.0.1.dist-info/METADATA
cg_rootutils-0.0.1.dist-info/LICENSE.md
cg_rootutils-0.0.1.dist-info/WHEEL
cg_rootutils-0.0.1.dist-info/RECORD
